dbt/adapters/teradata/__init__.py
dbt/adapters/teradata/__version__.py
dbt/adapters/teradata/column.py
dbt/adapters/teradata/connections.py
dbt/adapters/teradata/impl.py
dbt/adapters/teradata/relation.py
dbt/include/teradata/__init__.py
dbt/include/teradata/dbt_project.yml
dbt/include/teradata/sample_profiles.yml
dbt/include/teradata/macros/adapters.sql
dbt/include/teradata/macros/apply_grants.sql
dbt/include/teradata/macros/catalog.sql
dbt/include/teradata/macros/columns.sql
dbt/include/teradata/macros/metadata.sql
dbt/include/teradata/macros/show.sql
dbt/include/teradata/macros/dbt_external_tables/create_external_schema.sql
dbt/include/teradata/macros/dbt_external_tables/create_external_table.sql
dbt/include/teradata/macros/dbt_external_tables/get_external_build_plan.sql
dbt/include/teradata/macros/dbt_external_tables/helpers/dropif.sql
dbt/include/teradata/macros/materializations/incremental/helpers.sql
dbt/include/teradata/macros/materializations/incremental/incremental.sql
dbt/include/teradata/macros/materializations/incremental/strategies.sql
dbt/include/teradata/macros/materializations/seed/seed.sql
dbt/include/teradata/macros/materializations/snapshot/helpers.sql
dbt/include/teradata/macros/materializations/snapshot/snapshot.sql
dbt/include/teradata/macros/materializations/snapshot/snapshot_merge.sql
dbt/include/teradata/macros/materializations/snapshot/strategies.sql
dbt/include/teradata/macros/materializations/table/table.sql
dbt/include/teradata/macros/materializations/test/test.sql
dbt/include/teradata/macros/materializations/unit/get_fixture_sql.sql
dbt/include/teradata/macros/materializations/unit/unit.sql
dbt/include/teradata/macros/materializations/view/view.sql
dbt/include/teradata/macros/utils/date_trunc.sql
dbt/include/teradata/macros/utils/dateadd.sql
dbt/include/teradata/macros/utils/datediff.sql
dbt/include/teradata/macros/utils/generate_series.sql
dbt/include/teradata/macros/utils/hash.sql
dbt/include/teradata/macros/utils/replace.sql
dbt_teradata-1.10.1.dist-info/LICENSE
dbt_teradata-1.10.1.dist-info/METADATA
dbt_teradata-1.10.1.dist-info/WHEEL
dbt_teradata-1.10.1.dist-info/top_level.txt
dbt_teradata-1.10.1.dist-info/RECORD
