Metadata-Version: 2.1
Name: dbt-teradata
Version: 1.10.1
Summary: The Teradata adapter plugin for dbt (data build tool)
Home-page: https://github.com/Teradata/dbt-teradata
Author: Teradata Corporation
Author-email: developers@teradata.com
License: UNKNOWN
Platform: UNKNOWN
Classifier: Development Status :: 5 - Production/Stable
Classifier: License :: OSI Approved :: Apache Software License
Classifier: Operating System :: Microsoft :: Windows
Classifier: Operating System :: MacOS :: MacOS X
Classifier: Operating System :: POSIX :: Linux
Classifier: Programming Language :: Python :: 3.9
Classifier: Programming Language :: Python :: 3.10
Classifier: Programming Language :: Python :: 3.11
Classifier: Programming Language :: Python :: 3.12
Classifier: Programming Language :: Python :: 3.13
Requires-Python: >=3.9,<3.14
License-File: LICENSE
Requires-Dist: dbt-adapters>=1.17.2
Requires-Dist: dbt-common<2.0,>=1.13
Requires-Dist: teradatasql>=20.00.00.10
